randomorg_api/__init__.py
randomorg_api/main.py
randomorg_api-0.1.2.dist-info/METADATA
randomorg_api-0.1.2.dist-info/WHEEL
randomorg_api-0.1.2.dist-info/licenses/LICENSE
randomorg_api-0.1.2.dist-info/RECORD
