Metadata-Version: 2.4
Name: randomorg_api
Version: 0.1.2
Summary: a small pip module to generate true random numbers using random.org's api
Project-URL: Home-page, https://github.com/ellipticobj/random-module.git
Project-URL: Issues, https://github.com/ellipticobj/random-module/issues
Project-URL: Documentation, https://github.com/ellipticobj/random-module/DOCUMENTATION.md
Author-email: Natalie Luna <luna@hackclub.app>
License:                     GNU GENERAL PUBLIC LICENSE
License-File: LICENSE
Keywords: random,random number,random number generation,random number generator,random org,random.org,true random
Classifier: Development Status :: 3 - Alpha
Classifier: License :: OSI Approved :: GNU General Public License v3 (GPLv3)
Classifier: Operating System :: OS Independent
Classifier: Programming Language :: Python :: 3
Requires-Python: >=3.8
Requires-Dist: requests
